{"doc":" Cookie.Util\n\n @author xuxueli 2015-12-12 18:01:06\n","fields":[],"enumConstants":[],"methods":[{"name":"set","paramTypes":["javax.servlet.http.HttpServletResponse","java.lang.String","java.lang.String","boolean"],"doc":" 保存\n\n @param response\n @param key\n @param value\n @param ifRemember\n"},{"name":"set","paramTypes":["javax.servlet.http.HttpServletResponse","java.lang.String","java.lang.String","java.lang.String","java.lang.String","int","boolean"],"doc":" 保存\n\n @param response\n @param key\n @param value\n @param maxAge\n"},{"name":"getValue","paramTypes":["javax.servlet.http.HttpServletRequest","java.lang.String"],"doc":" 查询value\n\n @param request\n @param key\n @return\n"},{"name":"get","paramTypes":["javax.servlet.http.HttpServletRequest","java.lang.String"],"doc":" 查询Cookie\n\n @param request\n @param key\n"},{"name":"remove","paramTypes":["javax.servlet.http.HttpServletRequest","javax.servlet.http.HttpServletResponse","java.lang.String"],"doc":" 删除Cookie\n\n @param request\n @param response\n @param key\n"}],"constructors":[]}